takeaway/controllers/__init__.py
takeaway/controllers/app.py
takeaway/controllers/commands.py
takeaway/controllers/management.py
takeaway/core/__init__.py
takeaway/core/utils/__init__.py
takeaway/core/utils/version.py
takeaway/script/__init__.py
takeaway/script/order.py
takeaway/settings/__init__.py
takeaway/settings/fastapi/__init__.py
takeaway/settings/fastapi/container.py
takeaway/settings/fastapi/controller.py
takeaway/settings/fastapi/dbsetup.py
takeaway/settings/fastapi/docker.py
takeaway/settings/fastapi/env.py
takeaway/settings/fastapi/extension.py
takeaway/settings/fastapi/factories.py
takeaway/settings/fastapi/gitignore.py
takeaway/settings/fastapi/helpers.py
takeaway/settings/fastapi/main.py
takeaway/settings/fastapi/models.py
takeaway/settings/fastapi/prestart.py
takeaway/settings/fastapi/readme.py
takeaway/settings/fastapi/requirements.py
takeaway/settings/fastapi/schemas.py
takeaway/settings/fastapi/settings.py
takeaway/settings/fastapi/start.py
takeaway/settings/flask/__init__.py
takeaway/settings/flask/app.py
takeaway/settings/flask/app_factory.py
takeaway/settings/flask/db_conf.py
takeaway/settings/flask/docker.py
takeaway/settings/flask/env.py
takeaway/settings/flask/extension.py
takeaway/settings/flask/models.py
takeaway/settings/flask/readme.py
takeaway/settings/flask/requirements.py
takeaway/settings/flask/serializer.py
takeaway/settings/flask/server.py
takeaway/settings/flask/settings.py
takeaway/settings/flask/test.py
takeaway/settings/flask/utils.py
startapp-0.2.0.0.dist-info/LICENSE
startapp-0.2.0.0.dist-info/METADATA
startapp-0.2.0.0.dist-info/WHEEL
startapp-0.2.0.0.dist-info/entry_points.txt
startapp-0.2.0.0.dist-info/top_level.txt
startapp-0.2.0.0.dist-info/RECORD
