Metadata-Version: 2.1
Name: startapp
Version: 0.2.0.0
Summary: Simple startapp for fastapi and flask
Home-page: https://github.com/marlin-dev/startapp
Author: Tural Muradov, Sabuhi Shukurov
Author-email: tural_m@hotmail.com, sabuhi.shukurov@gmail.com
License: MIT
Platform: UNKNOWN
Classifier: Intended Audience :: Developers
Classifier: Topic :: Software Development :: Build Tools
Classifier: License :: OSI Approved :: MIT License
Classifier: Programming Language :: Python
Classifier: Programming Language :: Python :: 3
Classifier: Programming Language :: Python :: 3.6
Classifier: Programming Language :: Python :: 3.7
Classifier: Programming Language :: Python :: 3 :: Only
Classifier: License :: OSI Approved :: MIT License
Classifier: Operating System :: OS Independent
Requires-Dist: click
Requires-Dist: requests
